algotimer/Timer.py
algotimer/__init__.py
algo_timer-0.0.3.dist-info/LICENSE
algo_timer-0.0.3.dist-info/METADATA
algo_timer-0.0.3.dist-info/WHEEL
algo_timer-0.0.3.dist-info/top_level.txt
algo_timer-0.0.3.dist-info/RECORD
