Metadata-Version: 2.1
Name: algo-timer
Version: 0.0.3
Summary: An easy-to-use algorithms timer.
Home-page: https://github.com/shenxiangzhuang/algo-timer
Author: Xiangzhuang Shen
Author-email: datahonor@gmail.com
License: UNKNOWN
Platform: UNKNOWN
Classifier: Programming Language :: Python :: 3
Classifier: License :: OSI Approved :: MIT License
Classifier: Operating System :: OS Independent
Requires-Python: >=3.6
